hipscat/__init__.py
hipscat/_version.py
hipscat/py.typed
hipscat/catalog/__init__.py
hipscat/catalog/catalog.py
hipscat/catalog/catalog_info.py
hipscat/catalog/catalog_type.py
hipscat/catalog/partition_info.py
hipscat/catalog/association_catalog/__init__.py
hipscat/catalog/association_catalog/association_catalog.py
hipscat/catalog/association_catalog/association_catalog_info.py
hipscat/catalog/association_catalog/partition_join_info.py
hipscat/catalog/dataset/__init__.py
hipscat/catalog/dataset/base_catalog_info.py
hipscat/catalog/dataset/catalog_info_factory.py
hipscat/catalog/dataset/dataset.py
hipscat/catalog/healpix_dataset/__init__.py
hipscat/catalog/healpix_dataset/healpix_dataset.py
hipscat/catalog/index/__init__.py
hipscat/catalog/index/index_catalog.py
hipscat/catalog/index/index_catalog_info.py
hipscat/catalog/margin_cache/__init__.py
hipscat/catalog/margin_cache/margin_cache_catalog_info.py
hipscat/catalog/margin_cache/margin_catalog.py
hipscat/catalog/source_catalog/__init__.py
hipscat/catalog/source_catalog/source_catalog_info.py
hipscat/inspection/__init__.py
hipscat/inspection/almanac.py
hipscat/inspection/almanac_info.py
hipscat/inspection/visualize_catalog.py
hipscat/io/__init__.py
hipscat/io/parquet_metadata.py
hipscat/io/paths.py
hipscat/io/validation.py
hipscat/io/write_metadata.py
hipscat/io/file_io/__init__.py
hipscat/io/file_io/file_io.py
hipscat/io/file_io/file_pointer.py
hipscat/loaders/__init__.py
hipscat/loaders/read_from_hipscat.py
hipscat/pixel_math/__init__.py
hipscat/pixel_math/box_filter.py
hipscat/pixel_math/cone_filter.py
hipscat/pixel_math/filter.py
hipscat/pixel_math/healpix_pixel.py
hipscat/pixel_math/healpix_pixel_convertor.py
hipscat/pixel_math/healpix_pixel_function.py
hipscat/pixel_math/healpix_shim.py
hipscat/pixel_math/hipscat_id.py
hipscat/pixel_math/margin_bounding.py
hipscat/pixel_math/partition_stats.py
hipscat/pixel_math/pixel_margins.py
hipscat/pixel_math/polygon_filter.py
hipscat/pixel_math/validators.py
hipscat-0.3.9.dist-info/LICENSE
hipscat-0.3.9.dist-info/METADATA
hipscat-0.3.9.dist-info/WHEEL
hipscat-0.3.9.dist-info/top_level.txt
hipscat-0.3.9.dist-info/RECORD
