Metadata-Version: 2.1
Name: hipscat
Version: 0.3.9
Summary: Hierarchical Progressive Survey Catalog
Author-email: LINCC Frameworks <lincc-frameworks-team@lists.lsst.org>
License: BSD 3-Clause License
Project-URL: Source Code, https://github.com/astronomy-commons/hipscat
Classifier: Development Status :: 4 - Beta
Classifier: License :: OSI Approved :: BSD License
Classifier: Intended Audience :: Developers
Classifier: Intended Audience :: Science/Research
Classifier: Operating System :: OS Independent
Classifier: Programming Language :: Python
Requires-Python: >=3.9
License-File: LICENSE
Requires-Dist: aiohttp
Requires-Dist: astropy
Requires-Dist: fsspec >=2023.10.0
Requires-Dist: healpy
Requires-Dist: matplotlib <3.9,>=3.3
Requires-Dist: mocpy
Requires-Dist: numba >=0.58
Requires-Dist: numpy <3
Requires-Dist: pandas
Requires-Dist: pyarrow >=14.0.1
Requires-Dist: typing-extensions >=4.3.0
Provides-Extra: dev
Requires-Dist: adlfs ; extra == 'dev'
Requires-Dist: asv ==0.6.3 ; extra == 'dev'
Requires-Dist: black ; extra == 'dev'
Requires-Dist: jupyter ; extra == 'dev'
Requires-Dist: mypy ; extra == 'dev'
Requires-Dist: pre-commit ; extra == 'dev'
Requires-Dist: pylint ; extra == 'dev'
Requires-Dist: pytest ; extra == 'dev'
Requires-Dist: pytest-cov ; extra == 'dev'
Requires-Dist: pytest-mock ; extra == 'dev'
Requires-Dist: pytest-timeout ; extra == 'dev'
Requires-Dist: s3fs ; extra == 'dev'
